mtr/__init__.py
mtr/cli.py
mtr/config.py
mtr/logger.py
mtr/ssh.py
mtr/sync.py
mtr_cli-0.3.0.dist-info/METADATA
mtr_cli-0.3.0.dist-info/WHEEL
mtr_cli-0.3.0.dist-info/entry_points.txt
mtr_cli-0.3.0.dist-info/licenses/LICENSE
mtr_cli-0.3.0.dist-info/RECORD
