Metadata-Version: 2.4
Name: mtr-cli
Version: 0.3.0
Summary: A CLI tool for seamless local development and remote execution on GPU servers.
Project-URL: Homepage, https://github.com/lecoan/mtremote
Project-URL: Repository, https://github.com/lecoan/mtremote
Author: lecoan
License: MIT
License-File: LICENSE
Classifier: Development Status :: 4 - Beta
Classifier: Environment :: Console
Classifier: Intended Audience :: Developers
Classifier: License :: OSI Approved :: MIT License
Classifier: Programming Language :: Python :: 3
Classifier: Programming Language :: Python :: 3.10
Classifier: Programming Language :: Python :: 3.11
Classifier: Programming Language :: Python :: 3.12
Classifier: Programming Language :: Python :: 3.13
Classifier: Topic :: Software Development :: Build Tools
Classifier: Topic :: System :: Systems Administration
Requires-Python: >=3.10
Requires-Dist: click>=8.0.0
Requires-Dist: paramiko>=2.11.0
Requires-Dist: pyyaml>=6.0
Requires-Dist: rich>=12.0.0
